gpclient/__init__.py
gpclient/gpclient.py
gpclient/gpserviceaccount.py
gpclient/gptranslations.py
gp_python_client-1.1.2.dist-info/LICENSE.txt
gp_python_client-1.1.2.dist-info/METADATA
gp_python_client-1.1.2.dist-info/WHEEL
gp_python_client-1.1.2.dist-info/top_level.txt
gp_python_client-1.1.2.dist-info/RECORD
