Metadata-Version: 2.1
Name: gp-python-client
Version: 1.1.2
Summary: Python client for Globalization Pipeline on IBM Cloud
Home-page: https://github.com/IBM-Cloud/gp-python-client
Author: Farhan Arshad
Author-email: icuintl@us.ibm.com
License: Apache License Version 2.0
Keywords: client globalization pipline ibm bluemix
Platform: UNKNOWN
Classifier: Development Status :: 5 - Production/Stable
Classifier: Intended Audience :: Developers
Classifier: Topic :: Software Development :: Localization
Classifier: License :: OSI Approved :: Apache Software License
Classifier: Programming Language :: Python :: 2.7
Classifier: Programming Language :: Python :: 3
Classifier: Programming Language :: Python :: 3.2
Classifier: Programming Language :: Python :: 3.3
Classifier: Programming Language :: Python :: 3.4
Requires-Dist: requests
Requires-Dist: babel
Requires-Dist: dateutils
